fastapi_project_gen/__init__.py
fastapi_project_gen/generator.py
fastapi_project_gen-1.0.0.dist-info/LICENSE
fastapi_project_gen-1.0.0.dist-info/METADATA
fastapi_project_gen-1.0.0.dist-info/WHEEL
fastapi_project_gen-1.0.0.dist-info/entry_points.txt
fastapi_project_gen-1.0.0.dist-info/top_level.txt
fastapi_project_gen-1.0.0.dist-info/RECORD
