Metadata-Version: 2.1
Name: fastapi_project_gen
Version: 1.0.0
Summary: A CLI tool to generate FastAPI MVC project structure
Home-page: https://github.com/yourusername/fastapi_project_gen
Author: Your Name
Author-email: your_email@example.com
Classifier: Programming Language :: Python :: 3
Classifier: License :: OSI Approved :: MIT License
Classifier: Operating System :: OS Independent
Requires-Python: >=3.7
License-File: LICENSE
